night_sky_pi/__init__.py
night_sky_pi/app/__init__.py
night_sky_pi/app/capture/__init__.py
night_sky_pi/app/capture/exposure.py
night_sky_pi/app/capture/imaging.py
night_sky_pi/app/capture/reporting.py
night_sky_pi/app/configuration/__init__.py
night_sky_pi/app/configuration/configuration.py
night_sky_pi/app/configuration/core_configuration.py
night_sky_pi/app/configuration/module_configuration.py
night_sky_pi/app/configuration/nsp_configuration.py
night_sky_pi/app/housekeeping.py
night_sky_pi/app/main.py
night_sky_pi/app/observation/__init__.py
night_sky_pi/app/observation/data.py
night_sky_pi/app/observation/filesystem.py
night_sky_pi/app/observation/utils.py
night_sky_pi/app/packaging.py
night_sky_pi/app/utilities/__init__.py
night_sky_pi/app/utilities/conversions.py
night_sky_pi/app/utilities/mqtt_client.py
night_sky_pi/entry.py
night_sky_pi-2.0.3.dist-info/LICENSE
night_sky_pi-2.0.3.dist-info/METADATA
night_sky_pi-2.0.3.dist-info/WHEEL
night_sky_pi-2.0.3.dist-info/entry_points.txt
night_sky_pi-2.0.3.dist-info/RECORD
