Metadata-Version: 2.3
Name: night-sky-pi
Version: 2.0.3
Summary: Capture images from sunset till sunrise for processing off device.
License: MIT
Author: Joe McCarthy
Author-email: 179146301+joe-mccarthy@users.noreply.github.com
Maintainer: Joe McCarthy
Maintainer-email: 179146301+joe-mccarthy@users.noreply.github.com
Requires-Python: >=3.12,<4.0
Classifier: License :: OSI Approved :: MIT License
Classifier: Programming Language :: Python :: 3
Classifier: Programming Language :: Python :: 3.12
Classifier: Programming Language :: Python :: 3.13
Requires-Dist: dataclass-wizard (>=0.33,<0.36)
Requires-Dist: dataclasses-json (>=0.6.7,<0.7.0)
Requires-Dist: paho-mqtt (>=2.1.0,<3.0.0)
Requires-Dist: pillow (>=11.0.0,<12.0.0)
Requires-Dist: python-magic (>=0.4.27,<0.5.0)
Requires-Dist: suntime (==1.2.5)
Project-URL: Documentation, https://github.com/joe-mccarthy/night-sky-pi
Project-URL: Homepage, https://github.com/joe-mccarthy/night-sky-pi
Project-URL: Repository, https://github.com/joe-mccarthy/night-sky-pi
